[
  {
    "platform": "jd",
    "product_id": "3631002579",
    "name": "SOGAL 书柜",
    "price": 3085.0,
    "original_price": 3085.9,
    "sales": 4148,
    "comments_count": 100,
    "shop_name": "索菲亚官方旗舰店",
    "category": "家居/厨具",
    "url": "https://item.jd.com/3631002579.html",
    "crawl_time": "2025-12-15 17:28:26"
  },
  {
    "platform": "jd",
    "product_id": "6787511034",
    "name": "HUAWEI MateBook 14s",
    "price": 5373.9,
    "original_price": 6539.5,
    "sales": 8519,
    "comments_count": 100,
    "shop_name": "华为专营店",
    "category": "电脑/台式机",
    "url": "https://item.jd.com/6787511034.html",
    "crawl_time": "2025-12-15 15:09:17"
  },
  {
    "platform": "jd",
    "product_id": "8163681739",
    "name": "vivo Y100 18GB+256GB 白色",
    "price": 4163.0,
    "original_price": 4163.99,
    "sales": 8345,
    "comments_count": 100,
    "shop_name": "vivo京东自营旗舰店",
    "category": "手机/智能手机",
    "url": "https://item.jd.com/8163681739.html",
    "crawl_time": "2025-12-15 18:36:39"
  },
  {
    "platform": "jd",
    "product_id": "6969217865",
    "name": "Shiseido 红腰子精华",
    "price": 335.5,
    "original_price": 648.66,
    "sales": 46109,
    "comments_count": 100,
    "shop_name": "资生堂京东自营旗舰店",
    "category": "美妆/护肤品",
    "url": "https://item.jd.com/6969217865.html",
    "crawl_time": "2025-12-15 11:55:25"
  },
  {
    "platform": "jd",
    "product_id": "2180508237",
    "name": "KUKa 功能沙发",
    "price": 1870.66,
    "original_price": 2468.0,
    "sales": 1804,
    "comments_count": 100,
    "shop_name": "顾家官方旗舰店",
    "category": "家居/厨具",
    "url": "https://item.jd.com/2180508237.html",
    "crawl_time": "2025-12-15 21:37:56"
  },
  {
    "platform": "jd",
    "product_id": "5719381215",
    "name": "SK-II神仙水 30g",
    "price": 1829.88,
    "original_price": 1829.88,
    "sales": 44230,
    "comments_count": 100,
    "shop_name": "SK-II专营店",
    "category": "美妆/美发",
    "url": "https://item.jd.com/5719381215.html",
    "crawl_time": "2025-12-15 20:58:20"
  },
  {
    "platform": "jd",
    "product_id": "5741737915",
    "name": "索菲亚定制衣柜 灰色 皮革",
    "price": 17875.41,
    "original_price": 17875.41,
    "sales": 115,
    "comments_count": 17,
    "shop_name": "索菲亚专营店",
    "category": "家居/厨具",
    "url": "https://item.jd.com/5741737915.html",
    "crawl_time": "2025-12-15 15:40:08"
  },
  {
    "platform": "jd",
    "product_id": "1564725570",
    "name": "Shiseido 红腰子精华 旗舰版",
    "price": 824.8,
    "original_price": 1060.18,
    "sales": 59947,
    "comments_count": 100,
    "shop_name": "资生堂专营店",
    "category": "美妆/美发",
    "url": "https://item.jd.com/1564725570.html",
    "crawl_time": "2025-12-15 18:39:49"
  },
  {
    "platform": "jd",
    "product_id": "9207948605",
    "name": "IKEA 储物柜",
    "price": 1072.63,
    "original_price": 1129.98,
    "sales": 16596,
    "comments_count": 100,
    "shop_name": "宜家京东自营旗舰店",
    "category": "家居/灯具",
    "url": "https://item.jd.com/9207948605.html",
    "crawl_time": "2025-12-15 20:12:28"
  },
  {
    "platform": "jd",
    "product_id": "2845396155",
    "name": "顾家软床 胡桃色 板材",
    "price": 6549.66,
    "original_price": 7127.9,
    "sales": 718,
    "comments_count": 100,
    "shop_name": "顾家京东自营旗舰店",
    "category": "家居/装饰",
    "url": "https://item.jd.com/2845396155.html",
    "crawl_time": "2025-12-15 17:50:35"
  },
  {
    "platform": "jd",
    "product_id": "7848348683",
    "name": "CHEERS 按摩椅",
    "price": 2461.05,
    "original_price": 2749.39,
    "sales": 26232,
    "comments_count": 100,
    "shop_name": "芝华仕京东自营旗舰店",
    "category": "家居/家纺",
    "url": "https://item.jd.com/7848348683.html",
    "crawl_time": "2025-12-15 19:55:48"
  },
  {
    "platform": "jd",
    "product_id": "4586464347",
    "name": "罗技游戏鼠标 Pro版 银色",
    "price": 135.99,
    "original_price": 178.88,
    "sales": 25859,
    "comments_count": 100,
    "shop_name": "罗技京东自营旗舰店",
    "category": "数码/音箱",
    "url": "https://item.jd.com/4586464347.html",
    "crawl_time": "2025-12-15 14:19:34"
  },
  {
    "platform": "jd",
    "product_id": "9723895111",
    "name": "Panasonic 洗衣机XQG",
    "price": 6361.59,
    "original_price": 6361.59,
    "sales": 6495,
    "comments_count": 100,
    "shop_name": "松下京东自营旗舰店",
    "category": "家电/电视",
    "url": "https://item.jd.com/9723895111.html",
    "crawl_time": "2025-12-15 20:25:48"
  },
  {
    "platform": "jd",
    "product_id": "7541979775",
    "name": "LINSY 床垫",
    "price": 557.03,
    "original_price": 631.87,
    "sales": 19246,
    "comments_count": 100,
    "shop_name": "林氏木业京东自营旗舰店",
    "category": "家居/家纺",
    "url": "https://item.jd.com/7541979775.html",
    "crawl_time": "2025-12-15 20:06:15"
  },
  {
    "platform": "jd",
    "product_id": "1811771714",
    "name": "苹果MacBook MacBook Pro 16 M3 Pro 8GB 1024GB",
    "price": 11382.66,
    "original_price": 13072.0,
    "sales": 1574,
    "comments_count": 100,
    "shop_name": "苹果京东自营旗舰店",
    "category": "电脑/一体机",
    "url": "https://item.jd.com/1811771714.html",
    "crawl_time": "2025-12-15 20:51:52"
  },
  {
    "platform": "jd",
    "product_id": "8741551661",
    "name": "Canon G7 X相机",
    "price": 18702.88,
    "original_price": 20983.88,
    "sales": 2631,
    "comments_count": 100,
    "shop_name": "佳能店铺",
    "category": "数码/存储设备",
    "url": "https://item.jd.com/8741551661.html",
    "crawl_time": "2025-12-15 20:40:54"
  },
  {
    "platform": "taobao",
    "product_id": "6990211541",
    "name": "一加12 4GB+256GB 红色",
    "price": 5024.91,
    "original_price": 5505.55,
    "sales": 790,
    "comments_count": 92,
    "shop_name": "一加官方旗舰店",
    "category": "手机/游戏手机",
    "url": "https://item.taobao.com/item.htm?id=6990211541",
    "crawl_time": "2025-12-15 19:58:56"
  },
  {
    "platform": "taobao",
    "product_id": "6482358328",
    "name": "OPPO A3 Pro 12GB+64GB 银色",
    "price": 1391.99,
    "original_price": 1947.66,
    "sales": 17265,
    "comments_count": 100,
    "shop_name": "OPPO全球购",
    "category": "手机/拍照手机",
    "url": "https://item.taobao.com/item.htm?id=6482358328",
    "crawl_time": "2025-12-15 13:30:39"
  },
  {
    "platform": "taobao",
    "product_id": "6252864113",
    "name": "SOGAL 鞋柜",
    "price": 16525.88,
    "original_price": 16525.5,
    "sales": 667,
    "comments_count": 100,
    "shop_name": "索菲亚品牌旗舰店_7412",
    "category": "家居/灯具",
    "url": "https://item.taobao.com/item.htm?id=6252864113",
    "crawl_time": "2025-12-15 12:35:56"
  },
  {
    "platform": "taobao",
    "product_id": "6867251306",
    "name": "iQOO 11S 6GB+1024GB 粉色",
    "price": 4974.5,
    "original_price": 5319.66,
    "sales": 4043,
    "comments_count": 100,
    "shop_name": "iQOO企业店",
    "category": "手机/5G手机",
    "url": "https://item.taobao.com/item.htm?id=6867251306",
    "crawl_time": "2025-12-15 14:50:14"
  },
  {
    "platform": "taobao",
    "product_id": "6441327369",
    "name": "HP 暗影精灵9",
    "price": 12229.66,
    "original_price": 14055.66,
    "sales": 2276,
    "comments_count": 100,
    "shop_name": "惠普天猫超市",
    "category": "电脑/平板电脑",
    "url": "https://item.taobao.com/item.htm?id=6441327369",
    "crawl_time": "2025-12-15 19:44:12"
  },
  {
    "platform": "taobao",
    "product_id": "6763365927",
    "name": "小米Civi 4 4GB+128GB 紫色",
    "price": 3104.88,
    "original_price": 3104.5,
    "sales": 417,
    "comments_count": 68,
    "shop_name": "小米小店",
    "category": "手机/商务手机",
    "url": "https://item.taobao.com/item.htm?id=6763365927",
    "crawl_time": "2025-12-15 16:03:43"
  },
  {
    "platform": "taobao",
    "product_id": "6988379018",
    "name": "Florasis 散粉",
    "price": 214.66,
    "original_price": 379.5,
    "sales": 31147,
    "comments_count": 100,
    "shop_name": "花西子企业店",
    "category": "美妆/美容仪",
    "url": "https://item.taobao.com/item.htm?id=6988379018",
    "crawl_time": "2025-12-15 17:23:14"
  },
  {
    "platform": "taobao",
    "product_id": "6332014688",
    "name": "联想拯救者Y9000P i7-13700H 64GB 2048GB RTX 4060",
    "price": 19365.0,
    "original_price": 21304.88,
    "sales": 2384,
    "comments_count": 100,
    "shop_name": "联想官方旗舰店",
    "category": "电脑/轻薄本",
    "url": "https://item.taobao.com/item.htm?id=6332014688",
    "crawl_time": "2025-12-15 16:13:49"
  },
  {
    "platform": "taobao",
    "product_id": "6138505444",
    "name": "TCL空调KFR- 300L升 节能",
    "price": 4685.9,
    "original_price": 4685.0,
    "sales": 3243,
    "comments_count": 100,
    "shop_name": "TCL官方旗舰店",
    "category": "家电/小家电",
    "url": "https://item.taobao.com/item.htm?id=6138505444",
    "crawl_time": "2025-12-15 19:01:08"
  },
  {
    "platform": "taobao",
    "product_id": "6046246017",
    "name": "华为nova 12 12GB+128GB 黑色",
    "price": 4250.99,
    "original_price": 4830.66,
    "sales": 16667,
    "comments_count": 100,
    "shop_name": "华为官方旗舰店",
    "category": "手机/5G手机",
    "url": "https://item.taobao.com/item.htm?id=6046246017",
    "crawl_time": "2025-12-15 18:01:21"
  },
  {
    "platform": "taobao",
    "product_id": "6442917389",
    "name": "OPPO Find X7 8GB+256GB 银色",
    "price": 5830.5,
    "original_price": 6547.9,
    "sales": 1169,
    "comments_count": 100,
    "shop_name": "OPPO天猫超市",
    "category": "手机/智能手机",
    "url": "https://item.taobao.com/item.htm?id=6442917389",
    "crawl_time": "2025-12-15 13:16:15"
  },
  {
    "platform": "taobao",
    "product_id": "6617711053",
    "name": "顾家功能沙发 白色 金属",
    "price": 8677.67,
    "original_price": 8677.67,
    "sales": 952,
    "comments_count": 100,
    "shop_name": "顾家全球购",
    "category": "家居/家纺",
    "url": "https://item.taobao.com/item.htm?id=6617711053",
    "crawl_time": "2025-12-15 12:07:07"
  },
  {
    "platform": "taobao",
    "product_id": "6013113790",
    "name": "林氏木业实木餐桌 原木色 实木",
    "price": 3180.23,
    "original_price": 3180.23,
    "sales": 2706,
    "comments_count": 100,
    "shop_name": "林氏木业官方旗舰店",
    "category": "家居/家纺",
    "url": "https://item.taobao.com/item.htm?id=6013113790",
    "crawl_time": "2025-12-15 19:40:04"
  },
  {
    "platform": "taobao",
    "product_id": "6126872265",
    "name": "索菲亚定制衣柜 白色 布艺",
    "price": 7625.97,
    "original_price": 7625.97,
    "sales": 1584,
    "comments_count": 100,
    "shop_name": "索菲亚官方旗舰店_5945",
    "category": "家居/家纺",
    "url": "https://item.taobao.com/item.htm?id=6126872265",
    "crawl_time": "2025-12-15 13:17:36"
  },
  {
    "platform": "taobao",
    "product_id": "6919098751",
    "name": "Three Squirrels 碧根果",
    "price": 24.88,
    "original_price": 35.0,
    "sales": 48512,
    "comments_count": 100,
    "shop_name": "三只松鼠企业店",
    "category": "食品/饮料",
    "url": "https://item.taobao.com/item.htm?id=6919098751",
    "crawl_time": "2025-12-15 14:39:10"
  },
  {
    "platform": "taobao",
    "product_id": "6421832238",
    "name": "QuanU 餐桌椅",
    "price": 2388.9,
    "original_price": 3387.99,
    "sales": 26952,
    "comments_count": 100,
    "shop_name": "全友官方旗舰店",
    "category": "家居/灯具",
    "url": "https://item.taobao.com/item.htm?id=6421832238",
    "crawl_time": "2025-12-15 15:03:05"
  },
  {
    "platform": "pdd",
    "product_id": "221762678",
    "name": "阿迪达斯训练鞋 基础款 红色",
    "price": 1116.66,
    "original_price": 1246.0,
    "sales": 9209,
    "comments_count": 100,
    "shop_name": "阿迪达斯官方品牌店",
    "category": "服装/女装",
    "url": "https://mobile.yangkeduo.com/goods.html?goods_id=221762678",
    "crawl_time": "2025-12-15 16:25:30"
  },
  {
    "platform": "pdd",
    "product_id": "202706518",
    "name": "SOGAL 鞋柜 旗舰版",
    "price": 19030.88,
    "original_price": 23303.9,
    "sales": 1065,
    "comments_count": 100,
    "shop_name": "索菲亚工厂店",
    "category": "家居/灯具",
    "url": "https://mobile.yangkeduo.com/goods.html?goods_id=202706518",
    "crawl_time": "2025-12-15 17:13:57"
  },
  {
    "platform": "pdd",
    "product_id": "260753286",
    "name": "Apple iPhone SE 1024GB 灰色",
    "price": 9496.36,
    "original_price": 11063.38,
    "sales": 3052,
    "comments_count": 100,
    "shop_name": "苹果官方品牌店",
    "category": "手机/拍照手机",
    "url": "https://mobile.yangkeduo.com/goods.html?goods_id=260753286",
    "crawl_time": "2025-12-15 13:08:34"
  },
  {
    "platform": "pdd",
    "product_id": "286362610",
    "name": "全友布艺沙发 灰色 皮革",
    "price": 541.62,
    "original_price": 813.63,
    "sales": 5516,
    "comments_count": 100,
    "shop_name": "全友工厂店",
    "category": "家居/家具",
    "url": "https://mobile.yangkeduo.com/goods.html?goods_id=286362610",
    "crawl_time": "2025-12-15 22:04:22"
  },
  {
    "platform": "pdd",
    "product_id": "206806498",
    "name": "华为MateBook D 16 i9-13900H 64GB 256GB",
    "price": 4565.99,
    "original_price": 5204.5,
    "sales": 8509,
    "comments_count": 100,
    "shop_name": "华为官方品牌店",
    "category": "电脑/一体机",
    "url": "https://mobile.yangkeduo.com/goods.html?goods_id=206806498",
    "crawl_time": "2025-12-15 11:41:51"
  },
  {
    "platform": "pdd",
    "product_id": "278415781",
    "name": "罗技游戏鼠标 基础版 粉色",
    "price": 164.5,
    "original_price": 202.99,
    "sales": 37361,
    "comments_count": 100,
    "shop_name": "罗技工厂店",
    "category": "数码/手表",
    "url": "https://mobile.yangkeduo.com/goods.html?goods_id=278415781",
    "crawl_time": "2025-12-15 15:54:28"
  },
  {
    "platform": "pdd",
    "product_id": "210302696",
    "name": "iQOO Neo9 18GB+128GB 粉色",
    "price": 2544.5,
    "original_price": 3244.9,
    "sales": 38031,
    "comments_count": 100,
    "shop_name": "iQOO专卖店",
    "category": "手机/折叠屏手机",
    "url": "https://mobile.yangkeduo.com/goods.html?goods_id=210302696",
    "crawl_time": "2025-12-15 14:43:33"
  },
  {
    "platform": "pdd",
    "product_id": "215619489",
    "name": "Be&Cheery 零食组合",
    "price": 51.49,
    "original_price": 77.41,
    "sales": 10625,
    "comments_count": 100,
    "shop_name": "百草味官方品牌店",
    "category": "食品/生鲜",
    "url": "https://mobile.yangkeduo.com/goods.html?goods_id=215619489",
    "crawl_time": "2025-12-15 21:26:27"
  },
  {
    "platform": "pdd",
    "product_id": "254011076",
    "name": "SOGAL 鞋柜 升级版",
    "price": 27234.04,
    "original_price": 29270.12,
    "sales": 79,
    "comments_count": 12,
    "shop_name": "索菲亚店铺",
    "category": "家居/家具",
    "url": "https://mobile.yangkeduo.com/goods.html?goods_id=254011076",
    "crawl_time": "2025-12-15 13:20:27"
  },
  {
    "platform": "pdd",
    "product_id": "256064223",
    "name": "西门子冰箱KG 500L英寸 静音",
    "price": 9248.99,
    "original_price": 9248.66,
    "sales": 1496,
    "comments_count": 100,
    "shop_name": "西门子店铺",
    "category": "家电/电视",
    "url": "https://mobile.yangkeduo.com/goods.html?goods_id=256064223",
    "crawl_time": "2025-12-15 15:45:34"
  },
  {
    "platform": "pdd",
    "product_id": "213865201",
    "name": "Lenovo 拯救者Y9000P",
    "price": 5274.68,
    "original_price": 5274.68,
    "sales": 4238,
    "comments_count": 100,
    "shop_name": "联想工厂店",
    "category": "电脑/一体机",
    "url": "https://mobile.yangkeduo.com/goods.html?goods_id=213865201",
    "crawl_time": "2025-12-15 16:29:19"
  },
  {
    "platform": "pdd",
    "product_id": "211594761",
    "name": "Master Kong 冰红茶",
    "price": 15.66,
    "original_price": 16.99,
    "sales": 8262,
    "comments_count": 100,
    "shop_name": "康师傅官方品牌店",
    "category": "食品/饮料",
    "url": "https://mobile.yangkeduo.com/goods.html?goods_id=211594761",
    "crawl_time": "2025-12-15 19:27:26"
  },
  {
    "platform": "pdd",
    "product_id": "266309134",
    "name": "CHANDO 精华",
    "price": 62.5,
    "original_price": 71.0,
    "sales": 3814,
    "comments_count": 100,
    "shop_name": "自然堂官方品牌店",
    "category": "美妆/香水",
    "url": "https://mobile.yangkeduo.com/goods.html?goods_id=266309134",
    "crawl_time": "2025-12-15 17:47:04"
  },
  {
    "platform": "pdd",
    "product_id": "277492757",
    "name": "Apple MacBook Air 13",
    "price": 34897.0,
    "original_price": 41019.88,
    "sales": 1287,
    "comments_count": 100,
    "shop_name": "苹果工厂店",
    "category": "电脑/笔记本电脑",
    "url": "https://mobile.yangkeduo.com/goods.html?goods_id=277492757",
    "crawl_time": "2025-12-15 17:39:41"
  },
  {
    "platform": "pdd",
    "product_id": "207522265",
    "name": "Apple MacBook Pro 14",
    "price": 19554.9,
    "original_price": 21570.0,
    "sales": 1937,
    "comments_count": 100,
    "shop_name": "苹果旗舰店_3086",
    "category": "电脑/平板电脑",
    "url": "https://mobile.yangkeduo.com/goods.html?goods_id=207522265",
    "crawl_time": "2025-12-15 15:55:38"
  },
  {
    "platform": "pdd",
    "product_id": "246721637",
    "name": "良品铺子麻辣零食大礼包 1L",
    "price": 155.5,
    "original_price": 235.99,
    "sales": 46966,
    "comments_count": 100,
    "shop_name": "良品铺子特价店",
    "category": "食品/饮料",
    "url": "https://mobile.yangkeduo.com/goods.html?goods_id=246721637",
    "crawl_time": "2025-12-15 16:17:01"
  },
  {
    "platform": "pdd",
    "product_id": "271088157",
    "name": "Xiaomi 14",
    "price": 5088.03,
    "original_price": 5088.03,
    "sales": 2289,
    "comments_count": 100,
    "shop_name": "小米店铺",
    "category": "手机/5G手机",
    "url": "https://mobile.yangkeduo.com/goods.html?goods_id=271088157",
    "crawl_time": "2025-12-15 15:39:51"
  },
  {
    "platform": "jd",
    "product_id": "6047641056",
    "name": "荣耀100 8GB+256GB 灰色",
    "price": 4655.0,
    "original_price": 6595.9,
    "sales": 16560,
    "comments_count": 100,
    "shop_name": "荣耀专营店",
    "category": "手机/智能手机",
    "url": "https://item.jd.com/6047641056.html",
    "crawl_time": "2025-12-15 15:00:37"
  }
]